PyNeutralNews/Bulk.py
PyNeutralNews/Client.py
PyNeutralNews/Connector.py
PyNeutralNews/Customize.py
PyNeutralNews/Faq.py
PyNeutralNews/Intent.py
PyNeutralNews/Nlp.py
PyNeutralNews/User.py
PyNeutralNews/__init__.py
PyNeutralNews/ApiModels/Attributes.py
PyNeutralNews/ApiModels/Basic.py
PyNeutralNews/ApiModels/__init__.py
PyNeutralNews/ApiModels/Bulk/Requests.py
PyNeutralNews/ApiModels/Bulk/Responses.py
PyNeutralNews/ApiModels/Bulk/__init__.py
PyNeutralNews/ApiModels/Bulk/Examples/Requests.py
PyNeutralNews/ApiModels/Bulk/Examples/Responses.py
PyNeutralNews/ApiModels/Bulk/Examples/__init__.py
PyNeutralNews/ApiModels/Customize/Requests.py
PyNeutralNews/ApiModels/Customize/Responses.py
PyNeutralNews/ApiModels/Customize/__init__.py
PyNeutralNews/ApiModels/Customize/Examples/Requests.py
PyNeutralNews/ApiModels/Customize/Examples/Responses.py
PyNeutralNews/ApiModels/Customize/Examples/__init__.py
PyNeutralNews/ApiModels/Faq/Requests.py
PyNeutralNews/ApiModels/Faq/Responses.py
PyNeutralNews/ApiModels/Faq/__init__.py
PyNeutralNews/ApiModels/Faq/Examples/Requests.py
PyNeutralNews/ApiModels/Faq/Examples/Responses.py
PyNeutralNews/ApiModels/Faq/Examples/__init__.py
PyNeutralNews/ApiModels/Intent/Requests.py
PyNeutralNews/ApiModels/Intent/Responses.py
PyNeutralNews/ApiModels/Intent/__init__.py
PyNeutralNews/ApiModels/Intent/Examples/Requests.py
PyNeutralNews/ApiModels/Intent/Examples/Responses.py
PyNeutralNews/ApiModels/Intent/Examples/__init__.py
PyNeutralNews/ApiModels/Nlp/Requests.py
PyNeutralNews/ApiModels/Nlp/Responses.py
PyNeutralNews/ApiModels/Nlp/__init__.py
PyNeutralNews/ApiModels/Nlp/Examples/Requests.py
PyNeutralNews/ApiModels/Nlp/Examples/Responses.py
PyNeutralNews/ApiModels/Nlp/Examples/__init__.py
PyNeutralNews/ApiModels/User/Requests.py
PyNeutralNews/ApiModels/User/Responses.py
PyNeutralNews/ApiModels/User/__init__.py
PyNeutralNews/ApiModels/User/Examples/Requests.py
PyNeutralNews/ApiModels/User/Examples/Responses.py
PyNeutralNews-0.9.1.dist-info/METADATA
PyNeutralNews-0.9.1.dist-info/WHEEL
PyNeutralNews-0.9.1.dist-info/top_level.txt
PyNeutralNews-0.9.1.dist-info/RECORD
